[
    {
        "%vlocity_namespace%__BasePriceListId__c": {
            "%vlocity_namespace%__Code__c": "2018",
            "VlocityDataPackType": "VlocityLookupMatchingKeyObject",
            "VlocityLookupRecordSourceKey": "%vlocity_namespace%__PriceList__c/2018",
            "VlocityRecordSObjectType": "%vlocity_namespace%__PriceList__c"
        },
        "%vlocity_namespace%__DisplayText__c": "349",
        "%vlocity_namespace%__EffectiveFromDate__c": "2018-09-01T19:18:00.000Z",
        "%vlocity_namespace%__EffectiveUntilDate__c": "",
        "%vlocity_namespace%__GlobalKey__c": "58e2684b-0b8c-71d5-8d56-39ea29f2f760",
        "%vlocity_namespace%__IsActive__c": true,
        "%vlocity_namespace%__IsBasePrice__c": true,
        "%vlocity_namespace%__IsOverride__c": false,
        "%vlocity_namespace%__IsVirtualPrice__c": false,
        "%vlocity_namespace%__OfferId__c": "",
        "%vlocity_namespace%__PriceListId__c": {
            "%vlocity_namespace%__Code__c": "2018",
            "VlocityDataPackType": "VlocityLookupMatchingKeyObject",
            "VlocityLookupRecordSourceKey": "%vlocity_namespace%__PriceList__c/2018",
            "VlocityRecordSObjectType": "%vlocity_namespace%__PriceList__c"
        },
        "%vlocity_namespace%__PricingElementGlobalKey__c": "896d9605-45f3-754d-c460-5c7ac29acc14",
        "%vlocity_namespace%__PricingElementId__c": {
            "%vlocity_namespace%__GlobalKey__c": "b5dec6ba-8d3d-0aaa-87d4-786f259d3194",
            "VlocityDataPackType": "VlocityLookupMatchingKeyObject",
            "VlocityLookupRecordSourceKey": "%vlocity_namespace%__PricingElement__c/b5dec6ba-8d3d-0aaa-87d4-786f259d3194",
            "VlocityRecordSObjectType": "%vlocity_namespace%__PricingElement__c"
        },
        "%vlocity_namespace%__PricingMatrixBindingData__c": "",
        "%vlocity_namespace%__ProductId__c": {
            "%vlocity_namespace%__GlobalKey__c": "cf5caa5f-5474-3cc1-d99a-871e62efd346",
            "VlocityDataPackType": "VlocityMatchingKeyObject",
            "VlocityMatchingRecordSourceKey": "Product2/cf5caa5f-5474-3cc1-d99a-871e62efd346",
            "VlocityRecordSObjectType": "Product2"
        },
        "%vlocity_namespace%__PromotionId__c": "",
        "%vlocity_namespace%__PromotionItemId__c": "",
        "%vlocity_namespace%__RulesDescription__c": "",
        "%vlocity_namespace%__TimePlanId__c": "",
        "%vlocity_namespace%__TimePolicyId__c": "",
        "Name": "58e2684b-0b8c-71d5-8d56-39ea29f2f760",
        "VlocityDataPackType": "SObject",
        "VlocityRecordSObjectType": "%vlocity_namespace%__PriceListEntry__c",
        "VlocityRecordSourceKey": "%vlocity_namespace%__PriceListEntry__c/58e2684b-0b8c-71d5-8d56-39ea29f2f760"
    }
]