[
    {
        "%vlocity_namespace%__AddDate__c": "",
        "%vlocity_namespace%__AttributeAdjustmentComments__c": "",
        "%vlocity_namespace%__AttributeAdjustmentUnits__c": "",
        "%vlocity_namespace%__AttributeCategoryId__c": {
            "%vlocity_namespace%__Code__c": "MOBILE_HANDSET",
            "VlocityDataPackType": "VlocityLookupMatchingKeyObject",
            "VlocityLookupRecordSourceKey": "%vlocity_namespace%__AttributeCategory__c/MOBILE_HANDSET",
            "VlocityRecordSObjectType": "%vlocity_namespace%__AttributeCategory__c"
        },
        "%vlocity_namespace%__AttributeDisplayNameOverride__c": "Device Colour",
        "%vlocity_namespace%__AttributeDisplaySequence__c": "1",
        "%vlocity_namespace%__AttributeId__c": {
            "%vlocity_namespace%__Code__c": "DEVICE_COLOUR",
            "VlocityDataPackType": "VlocityLookupMatchingKeyObject",
            "VlocityLookupRecordSourceKey": "%vlocity_namespace%__Attribute__c/DEVICE_COLOUR",
            "VlocityRecordSObjectType": "%vlocity_namespace%__Attribute__c"
        },
        "%vlocity_namespace%__AttributeId__r.%vlocity_namespace%__Code__c": "DEVICE_COLOUR",
        "%vlocity_namespace%__ConfigurationDetail__c": "",
        "%vlocity_namespace%__CustomConfigUiTemplate__c": "",
        "%vlocity_namespace%__Data__c": "",
        "%vlocity_namespace%__DefaultPicklistEntryId__c": "",
        "%vlocity_namespace%__DefaultPicklistValueId__c": "",
        "%vlocity_namespace%__DisplaySequence__c": "11",
        "%vlocity_namespace%__EndStory__c": "",
        "%vlocity_namespace%__ExcludedPicklistEntryIds__c": "",
        "%vlocity_namespace%__ExcludedPicklistValues__c": "",
        "%vlocity_namespace%__FormatMask__c": "",
        "%vlocity_namespace%__GlobalKey__c": "c77fe259-cc13-aea3-3af5-c845c520c21f",
        "%vlocity_namespace%__HasRule__c": false,
        "%vlocity_namespace%__HelpText__c": "",
        "%vlocity_namespace%__IsActiveAssignment__c": true,
        "%vlocity_namespace%__IsActive__c": true,
        "%vlocity_namespace%__IsConfigurable__c": true,
        "%vlocity_namespace%__IsDynamic__c": false,
        "%vlocity_namespace%__IsHidden__c": false,
        "%vlocity_namespace%__IsOverride__c": false,
        "%vlocity_namespace%__IsQueryDriven__c": false,
        "%vlocity_namespace%__IsReadOnly__c": false,
        "%vlocity_namespace%__IsRequired__c": false,
        "%vlocity_namespace%__LookupFilter__c": "",
        "%vlocity_namespace%__LookupObjectId__c": "",
        "%vlocity_namespace%__LookupObjectTypeId__c": "",
        "%vlocity_namespace%__ObjectId__c": {
            "%vlocity_namespace%__GlobalKey__c": "36643765-b8ca-7d93-7273-fd659ff19d2d",
            "VlocityDataPackType": "VlocityMatchingKeyObject",
            "VlocityMatchingRecordSourceKey": "Product2/36643765-b8ca-7d93-7273-fd659ff19d2d",
            "VlocityRecordSObjectType": "Product2"
        },
        "%vlocity_namespace%__ObjectType__c": "Product2",
        "%vlocity_namespace%__PicklistId__c": {
            "%vlocity_namespace%__GlobalKey__c": "c161be87-9bc2-a779-b73d-de81d0611b37",
            "VlocityDataPackType": "VlocityLookupMatchingKeyObject",
            "VlocityLookupRecordSourceKey": "%vlocity_namespace%__Picklist__c/c161be87-9bc2-a779-b73d-de81d0611b37",
            "VlocityRecordSObjectType": "%vlocity_namespace%__Picklist__c"
        },
        "%vlocity_namespace%__QueryCode__c": "",
        "%vlocity_namespace%__QueryLabel__c": "",
        "%vlocity_namespace%__RemoveDate__c": "",
        "%vlocity_namespace%__RemovedFlag__c": false,
        "%vlocity_namespace%__RuleData__c": "",
        "%vlocity_namespace%__RuleMessage__c": "",
        "%vlocity_namespace%__StartStory__c": "",
        "%vlocity_namespace%__StyleClass__c": "",
        "%vlocity_namespace%__UIDisplayType__c": "Dropdown",
        "%vlocity_namespace%__ValidValuesData__c": [
            {
                "displayText": "Silver",
                "id": 1,
                "isDefault": false,
                "isEditable": false,
                "value": "Silver"
            },
            {
                "displayText": "Gold",
                "id": 2,
                "isDefault": false,
                "isEditable": false,
                "value": "Gold"
            },
            {
                "displayText": "Space Grey",
                "id": 3,
                "isDefault": false,
                "isEditable": false,
                "value": "Space Grey"
            }
        ],
        "%vlocity_namespace%__ValueDataType__c": "Picklist",
        "%vlocity_namespace%__ValueDescription__c": "",
        "%vlocity_namespace%__Value__c": "",
        "Name": "NEW_ATTRIBUTE-016",
        "VlocityDataPackType": "SObject",
        "VlocityRecordSObjectType": "%vlocity_namespace%__AttributeAssignment__c",
        "VlocityRecordSourceKey": "%vlocity_namespace%__AttributeAssignment__c/%vlocity_namespace%__Attribute__c/DEVICE_COLOUR/Product2/36643765-b8ca-7d93-7273-fd659ff19d2d/GlobalKey/c77fe259-cc13-aea3-3af5-c845c520c21f"
    },
    {
        "%vlocity_namespace%__AddDate__c": "",
        "%vlocity_namespace%__AttributeAdjustmentComments__c": "",
        "%vlocity_namespace%__AttributeAdjustmentUnits__c": "",
        "%vlocity_namespace%__AttributeCategoryId__c": {
            "%vlocity_namespace%__Code__c": "MOBILE_HANDSET",
            "VlocityDataPackType": "VlocityLookupMatchingKeyObject",
            "VlocityLookupRecordSourceKey": "%vlocity_namespace%__AttributeCategory__c/MOBILE_HANDSET",
            "VlocityRecordSObjectType": "%vlocity_namespace%__AttributeCategory__c"
        },
        "%vlocity_namespace%__AttributeDisplayNameOverride__c": "Device IMEI",
        "%vlocity_namespace%__AttributeDisplaySequence__c": "6",
        "%vlocity_namespace%__AttributeId__c": {
            "%vlocity_namespace%__Code__c": "DEVICE_IMEI",
            "VlocityDataPackType": "VlocityLookupMatchingKeyObject",
            "VlocityLookupRecordSourceKey": "%vlocity_namespace%__Attribute__c/DEVICE_IMEI",
            "VlocityRecordSObjectType": "%vlocity_namespace%__Attribute__c"
        },
        "%vlocity_namespace%__AttributeId__r.%vlocity_namespace%__Code__c": "DEVICE_IMEI",
        "%vlocity_namespace%__ConfigurationDetail__c": "",
        "%vlocity_namespace%__CustomConfigUiTemplate__c": "",
        "%vlocity_namespace%__Data__c": "",
        "%vlocity_namespace%__DefaultPicklistEntryId__c": "",
        "%vlocity_namespace%__DefaultPicklistValueId__c": "",
        "%vlocity_namespace%__DisplaySequence__c": "11",
        "%vlocity_namespace%__EndStory__c": "",
        "%vlocity_namespace%__ExcludedPicklistEntryIds__c": "",
        "%vlocity_namespace%__ExcludedPicklistValues__c": "",
        "%vlocity_namespace%__FormatMask__c": "",
        "%vlocity_namespace%__GlobalKey__c": "9e7bc83e-d41b-f546-4b63-43d4a295d0cf",
        "%vlocity_namespace%__HasRule__c": false,
        "%vlocity_namespace%__HelpText__c": "",
        "%vlocity_namespace%__IsActiveAssignment__c": true,
        "%vlocity_namespace%__IsActive__c": true,
        "%vlocity_namespace%__IsConfigurable__c": true,
        "%vlocity_namespace%__IsDynamic__c": false,
        "%vlocity_namespace%__IsHidden__c": false,
        "%vlocity_namespace%__IsOverride__c": false,
        "%vlocity_namespace%__IsQueryDriven__c": false,
        "%vlocity_namespace%__IsReadOnly__c": false,
        "%vlocity_namespace%__IsRequired__c": false,
        "%vlocity_namespace%__LookupFilter__c": "",
        "%vlocity_namespace%__LookupObjectId__c": "",
        "%vlocity_namespace%__LookupObjectTypeId__c": "",
        "%vlocity_namespace%__ObjectId__c": {
            "%vlocity_namespace%__GlobalKey__c": "36643765-b8ca-7d93-7273-fd659ff19d2d",
            "VlocityDataPackType": "VlocityMatchingKeyObject",
            "VlocityMatchingRecordSourceKey": "Product2/36643765-b8ca-7d93-7273-fd659ff19d2d",
            "VlocityRecordSObjectType": "Product2"
        },
        "%vlocity_namespace%__ObjectType__c": "Product2",
        "%vlocity_namespace%__PicklistId__c": "",
        "%vlocity_namespace%__QueryCode__c": "",
        "%vlocity_namespace%__QueryLabel__c": "",
        "%vlocity_namespace%__RemoveDate__c": "",
        "%vlocity_namespace%__RemovedFlag__c": false,
        "%vlocity_namespace%__RuleData__c": "",
        "%vlocity_namespace%__RuleMessage__c": "",
        "%vlocity_namespace%__StartStory__c": "",
        "%vlocity_namespace%__StyleClass__c": "",
        "%vlocity_namespace%__UIDisplayType__c": "",
        "%vlocity_namespace%__ValidValuesData__c": "",
        "%vlocity_namespace%__ValueDataType__c": "Text",
        "%vlocity_namespace%__ValueDescription__c": "",
        "%vlocity_namespace%__Value__c": "",
        "Name": "NEW_ATTRIBUTE-071",
        "VlocityDataPackType": "SObject",
        "VlocityRecordSObjectType": "%vlocity_namespace%__AttributeAssignment__c",
        "VlocityRecordSourceKey": "%vlocity_namespace%__AttributeAssignment__c/%vlocity_namespace%__Attribute__c/DEVICE_IMEI/Product2/36643765-b8ca-7d93-7273-fd659ff19d2d/GlobalKey/9e7bc83e-d41b-f546-4b63-43d4a295d0cf"
    },
    {
        "%vlocity_namespace%__AddDate__c": "",
        "%vlocity_namespace%__AttributeAdjustmentComments__c": "",
        "%vlocity_namespace%__AttributeAdjustmentUnits__c": "",
        "%vlocity_namespace%__AttributeCategoryId__c": {
            "%vlocity_namespace%__Code__c": "MOBILE_HANDSET",
            "VlocityDataPackType": "VlocityLookupMatchingKeyObject",
            "VlocityLookupRecordSourceKey": "%vlocity_namespace%__AttributeCategory__c/MOBILE_HANDSET",
            "VlocityRecordSObjectType": "%vlocity_namespace%__AttributeCategory__c"
        },
        "%vlocity_namespace%__AttributeDisplayNameOverride__c": "Device Manufacturer",
        "%vlocity_namespace%__AttributeDisplaySequence__c": "3",
        "%vlocity_namespace%__AttributeId__c": {
            "%vlocity_namespace%__Code__c": "DEVICE_MANUFACTURER",
            "VlocityDataPackType": "VlocityLookupMatchingKeyObject",
            "VlocityLookupRecordSourceKey": "%vlocity_namespace%__Attribute__c/DEVICE_MANUFACTURER",
            "VlocityRecordSObjectType": "%vlocity_namespace%__Attribute__c"
        },
        "%vlocity_namespace%__AttributeId__r.%vlocity_namespace%__Code__c": "DEVICE_MANUFACTURER",
        "%vlocity_namespace%__ConfigurationDetail__c": "",
        "%vlocity_namespace%__CustomConfigUiTemplate__c": "",
        "%vlocity_namespace%__Data__c": "",
        "%vlocity_namespace%__DefaultPicklistEntryId__c": "",
        "%vlocity_namespace%__DefaultPicklistValueId__c": "",
        "%vlocity_namespace%__DisplaySequence__c": "11",
        "%vlocity_namespace%__EndStory__c": "",
        "%vlocity_namespace%__ExcludedPicklistEntryIds__c": "",
        "%vlocity_namespace%__ExcludedPicklistValues__c": "",
        "%vlocity_namespace%__FormatMask__c": "",
        "%vlocity_namespace%__GlobalKey__c": "474e7a34-775e-5d87-30fe-58c2e013eb05",
        "%vlocity_namespace%__HasRule__c": false,
        "%vlocity_namespace%__HelpText__c": "",
        "%vlocity_namespace%__IsActiveAssignment__c": true,
        "%vlocity_namespace%__IsActive__c": true,
        "%vlocity_namespace%__IsConfigurable__c": false,
        "%vlocity_namespace%__IsDynamic__c": false,
        "%vlocity_namespace%__IsHidden__c": false,
        "%vlocity_namespace%__IsOverride__c": false,
        "%vlocity_namespace%__IsQueryDriven__c": false,
        "%vlocity_namespace%__IsReadOnly__c": false,
        "%vlocity_namespace%__IsRequired__c": false,
        "%vlocity_namespace%__LookupFilter__c": "",
        "%vlocity_namespace%__LookupObjectId__c": "",
        "%vlocity_namespace%__LookupObjectTypeId__c": "",
        "%vlocity_namespace%__ObjectId__c": {
            "%vlocity_namespace%__GlobalKey__c": "36643765-b8ca-7d93-7273-fd659ff19d2d",
            "VlocityDataPackType": "VlocityMatchingKeyObject",
            "VlocityMatchingRecordSourceKey": "Product2/36643765-b8ca-7d93-7273-fd659ff19d2d",
            "VlocityRecordSObjectType": "Product2"
        },
        "%vlocity_namespace%__ObjectType__c": "Product2",
        "%vlocity_namespace%__PicklistId__c": "",
        "%vlocity_namespace%__QueryCode__c": "",
        "%vlocity_namespace%__QueryLabel__c": "",
        "%vlocity_namespace%__RemoveDate__c": "",
        "%vlocity_namespace%__RemovedFlag__c": false,
        "%vlocity_namespace%__RuleData__c": "",
        "%vlocity_namespace%__RuleMessage__c": "",
        "%vlocity_namespace%__StartStory__c": "",
        "%vlocity_namespace%__StyleClass__c": "",
        "%vlocity_namespace%__UIDisplayType__c": "",
        "%vlocity_namespace%__ValidValuesData__c": "",
        "%vlocity_namespace%__ValueDataType__c": "Text",
        "%vlocity_namespace%__ValueDescription__c": "",
        "%vlocity_namespace%__Value__c": "Apple",
        "Name": "NEW_ATTRIBUTE-064",
        "VlocityDataPackType": "SObject",
        "VlocityRecordSObjectType": "%vlocity_namespace%__AttributeAssignment__c",
        "VlocityRecordSourceKey": "%vlocity_namespace%__AttributeAssignment__c/%vlocity_namespace%__Attribute__c/DEVICE_MANUFACTURER/Product2/36643765-b8ca-7d93-7273-fd659ff19d2d/GlobalKey/474e7a34-775e-5d87-30fe-58c2e013eb05"
    },
    {
        "%vlocity_namespace%__AddDate__c": "",
        "%vlocity_namespace%__AttributeAdjustmentComments__c": "",
        "%vlocity_namespace%__AttributeAdjustmentUnits__c": "",
        "%vlocity_namespace%__AttributeCategoryId__c": {
            "%vlocity_namespace%__Code__c": "MOBILE_HANDSET",
            "VlocityDataPackType": "VlocityLookupMatchingKeyObject",
            "VlocityLookupRecordSourceKey": "%vlocity_namespace%__AttributeCategory__c/MOBILE_HANDSET",
            "VlocityRecordSObjectType": "%vlocity_namespace%__AttributeCategory__c"
        },
        "%vlocity_namespace%__AttributeDisplayNameOverride__c": "Device Network Compatibility",
        "%vlocity_namespace%__AttributeDisplaySequence__c": "5",
        "%vlocity_namespace%__AttributeId__c": {
            "%vlocity_namespace%__Code__c": "DEVICE_NETWORK_COMPATIBILITY",
            "VlocityDataPackType": "VlocityLookupMatchingKeyObject",
            "VlocityLookupRecordSourceKey": "%vlocity_namespace%__Attribute__c/DEVICE_NETWORK_COMPATIBILITY",
            "VlocityRecordSObjectType": "%vlocity_namespace%__Attribute__c"
        },
        "%vlocity_namespace%__AttributeId__r.%vlocity_namespace%__Code__c": "DEVICE_NETWORK_COMPATIBILITY",
        "%vlocity_namespace%__ConfigurationDetail__c": "",
        "%vlocity_namespace%__CustomConfigUiTemplate__c": "",
        "%vlocity_namespace%__Data__c": "",
        "%vlocity_namespace%__DefaultPicklistEntryId__c": "",
        "%vlocity_namespace%__DefaultPicklistValueId__c": "",
        "%vlocity_namespace%__DisplaySequence__c": "11",
        "%vlocity_namespace%__EndStory__c": "",
        "%vlocity_namespace%__ExcludedPicklistEntryIds__c": "",
        "%vlocity_namespace%__ExcludedPicklistValues__c": "",
        "%vlocity_namespace%__FormatMask__c": "",
        "%vlocity_namespace%__GlobalKey__c": "076c87d5-ccc0-726a-5877-faa38ee39896",
        "%vlocity_namespace%__HasRule__c": false,
        "%vlocity_namespace%__HelpText__c": "",
        "%vlocity_namespace%__IsActiveAssignment__c": true,
        "%vlocity_namespace%__IsActive__c": true,
        "%vlocity_namespace%__IsConfigurable__c": false,
        "%vlocity_namespace%__IsDynamic__c": false,
        "%vlocity_namespace%__IsHidden__c": false,
        "%vlocity_namespace%__IsOverride__c": false,
        "%vlocity_namespace%__IsQueryDriven__c": false,
        "%vlocity_namespace%__IsReadOnly__c": false,
        "%vlocity_namespace%__IsRequired__c": false,
        "%vlocity_namespace%__LookupFilter__c": "",
        "%vlocity_namespace%__LookupObjectId__c": "",
        "%vlocity_namespace%__LookupObjectTypeId__c": "",
        "%vlocity_namespace%__ObjectId__c": {
            "%vlocity_namespace%__GlobalKey__c": "36643765-b8ca-7d93-7273-fd659ff19d2d",
            "VlocityDataPackType": "VlocityMatchingKeyObject",
            "VlocityMatchingRecordSourceKey": "Product2/36643765-b8ca-7d93-7273-fd659ff19d2d",
            "VlocityRecordSObjectType": "Product2"
        },
        "%vlocity_namespace%__ObjectType__c": "Product2",
        "%vlocity_namespace%__PicklistId__c": "",
        "%vlocity_namespace%__QueryCode__c": "",
        "%vlocity_namespace%__QueryLabel__c": "",
        "%vlocity_namespace%__RemoveDate__c": "",
        "%vlocity_namespace%__RemovedFlag__c": false,
        "%vlocity_namespace%__RuleData__c": "",
        "%vlocity_namespace%__RuleMessage__c": "",
        "%vlocity_namespace%__StartStory__c": "",
        "%vlocity_namespace%__StyleClass__c": "",
        "%vlocity_namespace%__UIDisplayType__c": "",
        "%vlocity_namespace%__ValidValuesData__c": "",
        "%vlocity_namespace%__ValueDataType__c": "Text",
        "%vlocity_namespace%__ValueDescription__c": "",
        "%vlocity_namespace%__Value__c": "4G",
        "Name": "NEW_ATTRIBUTE-066",
        "VlocityDataPackType": "SObject",
        "VlocityRecordSObjectType": "%vlocity_namespace%__AttributeAssignment__c",
        "VlocityRecordSourceKey": "%vlocity_namespace%__AttributeAssignment__c/%vlocity_namespace%__Attribute__c/DEVICE_NETWORK_COMPATIBILITY/Product2/36643765-b8ca-7d93-7273-fd659ff19d2d/GlobalKey/076c87d5-ccc0-726a-5877-faa38ee39896"
    },
    {
        "%vlocity_namespace%__AddDate__c": "",
        "%vlocity_namespace%__AttributeAdjustmentComments__c": "",
        "%vlocity_namespace%__AttributeAdjustmentUnits__c": "",
        "%vlocity_namespace%__AttributeCategoryId__c": {
            "%vlocity_namespace%__Code__c": "MOBILE_HANDSET",
            "VlocityDataPackType": "VlocityLookupMatchingKeyObject",
            "VlocityLookupRecordSourceKey": "%vlocity_namespace%__AttributeCategory__c/MOBILE_HANDSET",
            "VlocityRecordSObjectType": "%vlocity_namespace%__AttributeCategory__c"
        },
        "%vlocity_namespace%__AttributeDisplayNameOverride__c": "Device Operating System",
        "%vlocity_namespace%__AttributeDisplaySequence__c": "4",
        "%vlocity_namespace%__AttributeId__c": {
            "%vlocity_namespace%__Code__c": "DEVICE_OPERATING_SYSTEM",
            "VlocityDataPackType": "VlocityLookupMatchingKeyObject",
            "VlocityLookupRecordSourceKey": "%vlocity_namespace%__Attribute__c/DEVICE_OPERATING_SYSTEM",
            "VlocityRecordSObjectType": "%vlocity_namespace%__Attribute__c"
        },
        "%vlocity_namespace%__AttributeId__r.%vlocity_namespace%__Code__c": "DEVICE_OPERATING_SYSTEM",
        "%vlocity_namespace%__ConfigurationDetail__c": "",
        "%vlocity_namespace%__CustomConfigUiTemplate__c": "",
        "%vlocity_namespace%__Data__c": "",
        "%vlocity_namespace%__DefaultPicklistEntryId__c": "",
        "%vlocity_namespace%__DefaultPicklistValueId__c": "",
        "%vlocity_namespace%__DisplaySequence__c": "11",
        "%vlocity_namespace%__EndStory__c": "",
        "%vlocity_namespace%__ExcludedPicklistEntryIds__c": "",
        "%vlocity_namespace%__ExcludedPicklistValues__c": "",
        "%vlocity_namespace%__FormatMask__c": "",
        "%vlocity_namespace%__GlobalKey__c": "b031c63d-8666-1d1a-b230-7ebd01b24f74",
        "%vlocity_namespace%__HasRule__c": false,
        "%vlocity_namespace%__HelpText__c": "",
        "%vlocity_namespace%__IsActiveAssignment__c": true,
        "%vlocity_namespace%__IsActive__c": true,
        "%vlocity_namespace%__IsConfigurable__c": false,
        "%vlocity_namespace%__IsDynamic__c": false,
        "%vlocity_namespace%__IsHidden__c": false,
        "%vlocity_namespace%__IsOverride__c": false,
        "%vlocity_namespace%__IsQueryDriven__c": false,
        "%vlocity_namespace%__IsReadOnly__c": false,
        "%vlocity_namespace%__IsRequired__c": false,
        "%vlocity_namespace%__LookupFilter__c": "",
        "%vlocity_namespace%__LookupObjectId__c": "",
        "%vlocity_namespace%__LookupObjectTypeId__c": "",
        "%vlocity_namespace%__ObjectId__c": {
            "%vlocity_namespace%__GlobalKey__c": "36643765-b8ca-7d93-7273-fd659ff19d2d",
            "VlocityDataPackType": "VlocityMatchingKeyObject",
            "VlocityMatchingRecordSourceKey": "Product2/36643765-b8ca-7d93-7273-fd659ff19d2d",
            "VlocityRecordSObjectType": "Product2"
        },
        "%vlocity_namespace%__ObjectType__c": "Product2",
        "%vlocity_namespace%__PicklistId__c": {
            "%vlocity_namespace%__GlobalKey__c": "78449bfb-3e5b-e6de-7f13-c14be5decce7",
            "VlocityDataPackType": "VlocityLookupMatchingKeyObject",
            "VlocityLookupRecordSourceKey": "%vlocity_namespace%__Picklist__c/78449bfb-3e5b-e6de-7f13-c14be5decce7",
            "VlocityRecordSObjectType": "%vlocity_namespace%__Picklist__c"
        },
        "%vlocity_namespace%__QueryCode__c": "",
        "%vlocity_namespace%__QueryLabel__c": "",
        "%vlocity_namespace%__RemoveDate__c": "",
        "%vlocity_namespace%__RemovedFlag__c": false,
        "%vlocity_namespace%__RuleData__c": "",
        "%vlocity_namespace%__RuleMessage__c": "",
        "%vlocity_namespace%__StartStory__c": "",
        "%vlocity_namespace%__StyleClass__c": "",
        "%vlocity_namespace%__UIDisplayType__c": "",
        "%vlocity_namespace%__ValidValuesData__c": "",
        "%vlocity_namespace%__ValueDataType__c": "Text",
        "%vlocity_namespace%__ValueDescription__c": "",
        "%vlocity_namespace%__Value__c": "iOS",
        "Name": "NEW_ATTRIBUTE-065",
        "VlocityDataPackType": "SObject",
        "VlocityRecordSObjectType": "%vlocity_namespace%__AttributeAssignment__c",
        "VlocityRecordSourceKey": "%vlocity_namespace%__AttributeAssignment__c/%vlocity_namespace%__Attribute__c/DEVICE_OPERATING_SYSTEM/Product2/36643765-b8ca-7d93-7273-fd659ff19d2d/GlobalKey/b031c63d-8666-1d1a-b230-7ebd01b24f74"
    },
    {
        "%vlocity_namespace%__AddDate__c": "",
        "%vlocity_namespace%__AttributeAdjustmentComments__c": "",
        "%vlocity_namespace%__AttributeAdjustmentUnits__c": "",
        "%vlocity_namespace%__AttributeCategoryId__c": {
            "%vlocity_namespace%__Code__c": "MOBILE_HANDSET",
            "VlocityDataPackType": "VlocityLookupMatchingKeyObject",
            "VlocityLookupRecordSourceKey": "%vlocity_namespace%__AttributeCategory__c/MOBILE_HANDSET",
            "VlocityRecordSObjectType": "%vlocity_namespace%__AttributeCategory__c"
        },
        "%vlocity_namespace%__AttributeDisplayNameOverride__c": "Device Storage",
        "%vlocity_namespace%__AttributeDisplaySequence__c": "2",
        "%vlocity_namespace%__AttributeId__c": {
            "%vlocity_namespace%__Code__c": "DEVICE_STORAGE",
            "VlocityDataPackType": "VlocityLookupMatchingKeyObject",
            "VlocityLookupRecordSourceKey": "%vlocity_namespace%__Attribute__c/DEVICE_STORAGE",
            "VlocityRecordSObjectType": "%vlocity_namespace%__Attribute__c"
        },
        "%vlocity_namespace%__AttributeId__r.%vlocity_namespace%__Code__c": "DEVICE_STORAGE",
        "%vlocity_namespace%__ConfigurationDetail__c": "",
        "%vlocity_namespace%__CustomConfigUiTemplate__c": "",
        "%vlocity_namespace%__Data__c": "",
        "%vlocity_namespace%__DefaultPicklistEntryId__c": "",
        "%vlocity_namespace%__DefaultPicklistValueId__c": "",
        "%vlocity_namespace%__DisplaySequence__c": "11",
        "%vlocity_namespace%__EndStory__c": "",
        "%vlocity_namespace%__ExcludedPicklistEntryIds__c": "",
        "%vlocity_namespace%__ExcludedPicklistValues__c": "",
        "%vlocity_namespace%__FormatMask__c": "",
        "%vlocity_namespace%__GlobalKey__c": "7386633f-e584-a56d-138e-09ce18ac10be",
        "%vlocity_namespace%__HasRule__c": false,
        "%vlocity_namespace%__HelpText__c": "",
        "%vlocity_namespace%__IsActiveAssignment__c": true,
        "%vlocity_namespace%__IsActive__c": true,
        "%vlocity_namespace%__IsConfigurable__c": true,
        "%vlocity_namespace%__IsDynamic__c": false,
        "%vlocity_namespace%__IsHidden__c": false,
        "%vlocity_namespace%__IsOverride__c": false,
        "%vlocity_namespace%__IsQueryDriven__c": false,
        "%vlocity_namespace%__IsReadOnly__c": false,
        "%vlocity_namespace%__IsRequired__c": false,
        "%vlocity_namespace%__LookupFilter__c": "",
        "%vlocity_namespace%__LookupObjectId__c": "",
        "%vlocity_namespace%__LookupObjectTypeId__c": "",
        "%vlocity_namespace%__ObjectId__c": {
            "%vlocity_namespace%__GlobalKey__c": "36643765-b8ca-7d93-7273-fd659ff19d2d",
            "VlocityDataPackType": "VlocityMatchingKeyObject",
            "VlocityMatchingRecordSourceKey": "Product2/36643765-b8ca-7d93-7273-fd659ff19d2d",
            "VlocityRecordSObjectType": "Product2"
        },
        "%vlocity_namespace%__ObjectType__c": "Product2",
        "%vlocity_namespace%__PicklistId__c": {
            "%vlocity_namespace%__GlobalKey__c": "b7afdfbb-4e48-c827-5281-74a8c8ea0168",
            "VlocityDataPackType": "VlocityLookupMatchingKeyObject",
            "VlocityLookupRecordSourceKey": "%vlocity_namespace%__Picklist__c/b7afdfbb-4e48-c827-5281-74a8c8ea0168",
            "VlocityRecordSObjectType": "%vlocity_namespace%__Picklist__c"
        },
        "%vlocity_namespace%__QueryCode__c": "",
        "%vlocity_namespace%__QueryLabel__c": "",
        "%vlocity_namespace%__RemoveDate__c": "",
        "%vlocity_namespace%__RemovedFlag__c": false,
        "%vlocity_namespace%__RuleData__c": "",
        "%vlocity_namespace%__RuleMessage__c": "",
        "%vlocity_namespace%__StartStory__c": "",
        "%vlocity_namespace%__StyleClass__c": "",
        "%vlocity_namespace%__UIDisplayType__c": "Dropdown",
        "%vlocity_namespace%__ValidValuesData__c": [
            {
                "displayText": "16GB",
                "id": 1,
                "isDefault": false,
                "isEditable": false,
                "value": "16GB"
            },
            {
                "displayText": "32GB",
                "id": 2,
                "isDefault": false,
                "isEditable": false,
                "value": "32GB"
            },
            {
                "displayText": "64GB",
                "id": 3,
                "isDefault": false,
                "isEditable": false,
                "value": "64GB"
            },
            {
                "displayText": "128GB",
                "id": 4,
                "isDefault": false,
                "isEditable": false,
                "value": "128GB"
            }
        ],
        "%vlocity_namespace%__ValueDataType__c": "Picklist",
        "%vlocity_namespace%__ValueDescription__c": "",
        "%vlocity_namespace%__Value__c": "",
        "Name": "NEW_ATTRIBUTE-017",
        "VlocityDataPackType": "SObject",
        "VlocityRecordSObjectType": "%vlocity_namespace%__AttributeAssignment__c",
        "VlocityRecordSourceKey": "%vlocity_namespace%__AttributeAssignment__c/%vlocity_namespace%__Attribute__c/DEVICE_STORAGE/Product2/36643765-b8ca-7d93-7273-fd659ff19d2d/GlobalKey/7386633f-e584-a56d-138e-09ce18ac10be"
    },
    {
        "%vlocity_namespace%__AddDate__c": "",
        "%vlocity_namespace%__AttributeAdjustmentComments__c": "",
        "%vlocity_namespace%__AttributeAdjustmentUnits__c": "",
        "%vlocity_namespace%__AttributeCategoryId__c": {
            "%vlocity_namespace%__Code__c": "MOBILE_TRADE_IN",
            "VlocityDataPackType": "VlocityLookupMatchingKeyObject",
            "VlocityLookupRecordSourceKey": "%vlocity_namespace%__AttributeCategory__c/MOBILE_TRADE_IN",
            "VlocityRecordSObjectType": "%vlocity_namespace%__AttributeCategory__c"
        },
        "%vlocity_namespace%__AttributeDisplayNameOverride__c": "Handset Condition",
        "%vlocity_namespace%__AttributeDisplaySequence__c": "2",
        "%vlocity_namespace%__AttributeId__c": {
            "%vlocity_namespace%__Code__c": "HANDSET_CONDITION",
            "VlocityDataPackType": "VlocityLookupMatchingKeyObject",
            "VlocityLookupRecordSourceKey": "%vlocity_namespace%__Attribute__c/HANDSET_CONDITION",
            "VlocityRecordSObjectType": "%vlocity_namespace%__Attribute__c"
        },
        "%vlocity_namespace%__AttributeId__r.%vlocity_namespace%__Code__c": "HANDSET_CONDITION",
        "%vlocity_namespace%__ConfigurationDetail__c": "",
        "%vlocity_namespace%__CustomConfigUiTemplate__c": "",
        "%vlocity_namespace%__Data__c": "",
        "%vlocity_namespace%__DefaultPicklistEntryId__c": "",
        "%vlocity_namespace%__DefaultPicklistValueId__c": "",
        "%vlocity_namespace%__DisplaySequence__c": "null",
        "%vlocity_namespace%__EndStory__c": "",
        "%vlocity_namespace%__ExcludedPicklistEntryIds__c": "",
        "%vlocity_namespace%__ExcludedPicklistValues__c": "",
        "%vlocity_namespace%__FormatMask__c": "",
        "%vlocity_namespace%__GlobalKey__c": "c32fc9c9-573f-b3ac-524a-19fde73b061e",
        "%vlocity_namespace%__HasRule__c": false,
        "%vlocity_namespace%__HelpText__c": "",
        "%vlocity_namespace%__IsActiveAssignment__c": true,
        "%vlocity_namespace%__IsActive__c": true,
        "%vlocity_namespace%__IsConfigurable__c": false,
        "%vlocity_namespace%__IsDynamic__c": false,
        "%vlocity_namespace%__IsHidden__c": false,
        "%vlocity_namespace%__IsOverride__c": false,
        "%vlocity_namespace%__IsQueryDriven__c": false,
        "%vlocity_namespace%__IsReadOnly__c": false,
        "%vlocity_namespace%__IsRequired__c": false,
        "%vlocity_namespace%__LookupFilter__c": "",
        "%vlocity_namespace%__LookupObjectId__c": "",
        "%vlocity_namespace%__LookupObjectTypeId__c": "",
        "%vlocity_namespace%__ObjectId__c": {
            "%vlocity_namespace%__GlobalKey__c": "36643765-b8ca-7d93-7273-fd659ff19d2d",
            "VlocityDataPackType": "VlocityMatchingKeyObject",
            "VlocityMatchingRecordSourceKey": "Product2/36643765-b8ca-7d93-7273-fd659ff19d2d",
            "VlocityRecordSObjectType": "Product2"
        },
        "%vlocity_namespace%__ObjectType__c": "Product2",
        "%vlocity_namespace%__PicklistId__c": "",
        "%vlocity_namespace%__QueryCode__c": "",
        "%vlocity_namespace%__QueryLabel__c": "",
        "%vlocity_namespace%__RemoveDate__c": "",
        "%vlocity_namespace%__RemovedFlag__c": false,
        "%vlocity_namespace%__RuleData__c": "",
        "%vlocity_namespace%__RuleMessage__c": "",
        "%vlocity_namespace%__StartStory__c": "",
        "%vlocity_namespace%__StyleClass__c": "",
        "%vlocity_namespace%__UIDisplayType__c": "",
        "%vlocity_namespace%__ValidValuesData__c": "",
        "%vlocity_namespace%__ValueDataType__c": "Text",
        "%vlocity_namespace%__ValueDescription__c": "",
        "%vlocity_namespace%__Value__c": "",
        "Name": "TempAA-ATTRIBUTE-139",
        "VlocityDataPackType": "SObject",
        "VlocityRecordSObjectType": "%vlocity_namespace%__AttributeAssignment__c",
        "VlocityRecordSourceKey": "%vlocity_namespace%__AttributeAssignment__c/%vlocity_namespace%__Attribute__c/HANDSET_CONDITION/Product2/36643765-b8ca-7d93-7273-fd659ff19d2d/GlobalKey/c32fc9c9-573f-b3ac-524a-19fde73b061e"
    },
    {
        "%vlocity_namespace%__AddDate__c": "",
        "%vlocity_namespace%__AttributeAdjustmentComments__c": "",
        "%vlocity_namespace%__AttributeAdjustmentUnits__c": "",
        "%vlocity_namespace%__AttributeCategoryId__c": {
            "%vlocity_namespace%__Code__c": "MOBILE_TRADE_IN",
            "VlocityDataPackType": "VlocityLookupMatchingKeyObject",
            "VlocityLookupRecordSourceKey": "%vlocity_namespace%__AttributeCategory__c/MOBILE_TRADE_IN",
            "VlocityRecordSObjectType": "%vlocity_namespace%__AttributeCategory__c"
        },
        "%vlocity_namespace%__AttributeDisplayNameOverride__c": "Handset Type",
        "%vlocity_namespace%__AttributeDisplaySequence__c": "1",
        "%vlocity_namespace%__AttributeId__c": {
            "%vlocity_namespace%__Code__c": "HANDSET_TYPE",
            "VlocityDataPackType": "VlocityLookupMatchingKeyObject",
            "VlocityLookupRecordSourceKey": "%vlocity_namespace%__Attribute__c/HANDSET_TYPE",
            "VlocityRecordSObjectType": "%vlocity_namespace%__Attribute__c"
        },
        "%vlocity_namespace%__AttributeId__r.%vlocity_namespace%__Code__c": "HANDSET_TYPE",
        "%vlocity_namespace%__ConfigurationDetail__c": "",
        "%vlocity_namespace%__CustomConfigUiTemplate__c": "",
        "%vlocity_namespace%__Data__c": "",
        "%vlocity_namespace%__DefaultPicklistEntryId__c": "",
        "%vlocity_namespace%__DefaultPicklistValueId__c": "",
        "%vlocity_namespace%__DisplaySequence__c": "null",
        "%vlocity_namespace%__EndStory__c": "",
        "%vlocity_namespace%__ExcludedPicklistEntryIds__c": "",
        "%vlocity_namespace%__ExcludedPicklistValues__c": "",
        "%vlocity_namespace%__FormatMask__c": "",
        "%vlocity_namespace%__GlobalKey__c": "9644f467-e786-18bb-9b1a-514bdecc3386",
        "%vlocity_namespace%__HasRule__c": false,
        "%vlocity_namespace%__HelpText__c": "",
        "%vlocity_namespace%__IsActiveAssignment__c": true,
        "%vlocity_namespace%__IsActive__c": true,
        "%vlocity_namespace%__IsConfigurable__c": false,
        "%vlocity_namespace%__IsDynamic__c": false,
        "%vlocity_namespace%__IsHidden__c": false,
        "%vlocity_namespace%__IsOverride__c": false,
        "%vlocity_namespace%__IsQueryDriven__c": false,
        "%vlocity_namespace%__IsReadOnly__c": false,
        "%vlocity_namespace%__IsRequired__c": false,
        "%vlocity_namespace%__LookupFilter__c": "",
        "%vlocity_namespace%__LookupObjectId__c": "",
        "%vlocity_namespace%__LookupObjectTypeId__c": "",
        "%vlocity_namespace%__ObjectId__c": {
            "%vlocity_namespace%__GlobalKey__c": "36643765-b8ca-7d93-7273-fd659ff19d2d",
            "VlocityDataPackType": "VlocityMatchingKeyObject",
            "VlocityMatchingRecordSourceKey": "Product2/36643765-b8ca-7d93-7273-fd659ff19d2d",
            "VlocityRecordSObjectType": "Product2"
        },
        "%vlocity_namespace%__ObjectType__c": "Product2",
        "%vlocity_namespace%__PicklistId__c": "",
        "%vlocity_namespace%__QueryCode__c": "",
        "%vlocity_namespace%__QueryLabel__c": "",
        "%vlocity_namespace%__RemoveDate__c": "",
        "%vlocity_namespace%__RemovedFlag__c": false,
        "%vlocity_namespace%__RuleData__c": "",
        "%vlocity_namespace%__RuleMessage__c": "",
        "%vlocity_namespace%__StartStory__c": "",
        "%vlocity_namespace%__StyleClass__c": "",
        "%vlocity_namespace%__UIDisplayType__c": "",
        "%vlocity_namespace%__ValidValuesData__c": "",
        "%vlocity_namespace%__ValueDataType__c": "Text",
        "%vlocity_namespace%__ValueDescription__c": "",
        "%vlocity_namespace%__Value__c": "",
        "Name": "TempAA-ATTRIBUTE-138",
        "VlocityDataPackType": "SObject",
        "VlocityRecordSObjectType": "%vlocity_namespace%__AttributeAssignment__c",
        "VlocityRecordSourceKey": "%vlocity_namespace%__AttributeAssignment__c/%vlocity_namespace%__Attribute__c/HANDSET_TYPE/Product2/36643765-b8ca-7d93-7273-fd659ff19d2d/GlobalKey/9644f467-e786-18bb-9b1a-514bdecc3386"
    }
]